stophana/__init__.py
stophana/main.py
stophana-1.0.dist-info/LICENSE
stophana-1.0.dist-info/METADATA
stophana-1.0.dist-info/WHEEL
stophana-1.0.dist-info/top_level.txt
stophana-1.0.dist-info/RECORD
